{"id":"758356537126682634","username":";; __TheToxic'$ ``","roles":[],"joinedAt":1654092212954,"leavedAt":null,"birthday":[8,18],"counting":{"lastScore":0,"bestScore":0,"timeLastScore":null,"timeBestScore":null,"correct":0,"incorrect":0,"streak":0,"updated":0,"deleted":0},"countingplus":{"lastScore":0,"timeLastScore":null,"correct":0,"incorrect":0,"streak":0,"updated":0,"deleted":0},"onewordstory":{"totWords":0,"totWordsToday":0,"totStories":0},"leveling":{"level":8,"xp":2051,"livelliSuperati":{"1":true,"8":true}},"economy":{"money":90,"inventory":{}},"moderation":{"type":"","since":null,"until":null,"reason":null,"moderator":null,"ticketOpened":false},"warns":[],"invites":{}}