{"id":"538075870011588619","username":"Endemuyh","roles":[],"joinedAt":1643384414285,"leavedAt":null,"birthday":[10,6],"counting":{"lastScore":17,"bestScore":225,"timeLastScore":1654879593715,"timeBestScore":1654866136630,"correct":181,"incorrect":3,"streak":90,"updated":0,"deleted":0},"countingplus":{"lastScore":0,"timeLastScore":null,"correct":0,"incorrect":0,"streak":0,"updated":0,"deleted":0},"onewordstory":{"totWords":0,"totWordsToday":0,"totStories":0},"leveling":{"level":36,"xp":45025,"livelliSuperati":{"1":true,"6":true,"8":true,"31":true,"32":true,"33":true,"34":true,"35":true,"36":true,"37":true}},"economy":{"money":2614,"inventory":{}},"moderation":{"type":"","since":null,"until":null,"reason":null,"moderator":null,"ticketOpened":false},"warns":[],"invites":{}}