{"id":"398189280515850242","username":"el_dylanius","roles":[],"joinedAt":{"$numberLong":"1645460704348"},"leavedAt":{"$numberLong":"1649362528110"},"birthday":[null,null],"counting":{"lastScore":10,"bestScore":10,"timeLastScore":{"$numberLong":"1645461118855"},"timeBestScore":{"$numberLong":"1645461118855"},"correct":1,"incorrect":0,"streak":0,"updated":0,"deleted":0},"countingplus":{"lastScore":0,"timeLastScore":null,"correct":0,"incorrect":0,"streak":0,"updated":0,"deleted":0},"onewordstory":{"totWords":0,"totWordsToday":0,"totStories":0},"leveling":{"level":2,"xp":284,"livelliSuperati":[null,true,true]},"economy":{"money":31,"inventory":{}},"moderation":{"type":"","since":null,"until":null,"reason":null,"moderator":null,"ticketOpened":false},"warns":[],"invites":{}}