{"id":"489078692266508298","username":"_.federica09._#6021","roles":[],"joinedAt":1657481322213,"leavedAt":null,"birthday":[],"counting":{"lastScore":11,"bestScore":45,"timeLastScore":1657643737529,"timeBestScore":1657482115294,"correct":5,"incorrect":0,"streak":5,"updated":0,"deleted":0},"countingplus":{"lastScore":0,"timeLastScore":null,"correct":0,"incorrect":0,"streak":0,"updated":0,"deleted":0},"onewordstory":{"totWords":0,"totWordsToday":0,"totStories":0},"leveling":{"level":2,"xp":242,"livelliSuperati":{"1":true,"2":true}},"economy":{"money":30,"inventory":{}},"moderation":{"type":"","since":"","until":"","reason":"","moderator":"","ticketOpened":false},"warns":[],"invites":{}}