{"id":"712702022515687426","username":"GabriX","roles":[],"joinedAt":1651845118169,"leavedAt":null,"birthday":[null,null],"counting":{"lastScore":48,"bestScore":48,"timeLastScore":1658989004559,"timeBestScore":1658989004559,"correct":15,"incorrect":6,"streak":2,"updated":0,"deleted":0},"countingplus":{"lastScore":0,"timeLastScore":null,"correct":0,"incorrect":0,"streak":0,"updated":0,"deleted":0},"onewordstory":{"totWords":4,"totWordsToday":0,"totStories":0},"leveling":{"level":12,"xp":3956,"livelliSuperati":{"11":true,"12":true}},"economy":{"money":481,"inventory":{}},"moderation":{"type":"","since":null,"until":null,"reason":null,"moderator":null,"ticketOpened":false},"warns":[],"invites":{}}