{"id":"784871834415923220","username":"!Ema#0104","roles":["799990865001971722","815649916574629941","883062518774370345","826784690487951370","815649625591382077","857544584691318814"],"joinedAt":{"$numberLong":"1638379628986"},"leavedAt":{"$numberLong":"1655480211452"},"birthday":[5,4],"counting":{"lastScore":16,"bestScore":122,"timeLastScore":{"$numberLong":"1653587399147"},"timeBestScore":{"$numberLong":"1645632082088"},"correct":47,"incorrect":0,"streak":6,"updated":0,"deleted":0},"countingplus":{"lastScore":-260,"timeLastScore":{"$numberLong":"1654981437247"},"correct":38,"incorrect":3,"streak":36,"updated":0,"deleted":0},"onewordstory":{"totWords":0,"totWordsToday":0,"totStories":0},"leveling":{"level":33,"xp":35032.700000000026,"livelliSuperati":[null,true,true,true,true,true,true,true,true,true,true,true,true,true,true,true,true,true,true,true,true,true,true,true,true,true,true,true,true,true,true,true,true,true]},"economy":{"money":3351,"inventory":{}},"moderation":{"type":"","since":null,"until":null,"reason":null,"moderator":null,"ticketOpened":false},"warns":[],"invites":{}}