{"id":"824636032765919262","username":"Gegy#7998","roles":[],"joinedAt":{"$numberLong":"1625006171208"},"leavedAt":null,"birthday":[],"counting":{"lastScore":9,"bestScore":365,"timeLastScore":{"$numberLong":"1626607782953"},"timeBestScore":"1625931309129","correct":382,"incorrect":11,"streak":0,"updated":0,"deleted":0},"countingplus":{"lastScore":0,"timeLastScore":null,"correct":0,"incorrect":0,"streak":0,"updated":0,"deleted":0},"onewordstory":{"totWords":0,"totWordsToday":0,"totStories":0},"leveling":{"level":13,"xp":4644,"livelliSuperati":{}},"economy":{"money":0,"inventory":{}},"moderation":{"type":"","since":null,"until":null,"reason":null,"moderator":null,"ticketOpened":false},"warns":[],"invites":{}}