{"id":"867452622045446164","username":"Tomas12","roles":["799990773708750878"],"joinedAt":1651006125413,"leavedAt":1658424204657,"birthday":[12,11],"counting":{"lastScore":13,"bestScore":40,"timeLastScore":1653984581337,"timeBestScore":1651828257894,"correct":21,"incorrect":0,"streak":21,"updated":0,"deleted":0},"countingplus":{"lastScore":0,"timeLastScore":null,"correct":0,"incorrect":0,"streak":0,"updated":0,"deleted":0},"onewordstory":{"totWords":0,"totWordsToday":0,"totStories":0},"leveling":{"level":17,"xp":8606,"livelliSuperati":{}},"economy":{"money":1533,"inventory":{}},"moderation":{"type":"","since":null,"until":null,"reason":null,"moderator":null,"ticketOpened":false},"warns":[{"type":"warn","reason":"ping a tutto lo staff nei ticket","time":1651329976330,"moderator":"802184359120863272"}],"invites":{}}