{"id":"935502675548721173","username":"Furye","roles":["799990705216159791"],"joinedAt":1651360246623,"leavedAt":1657727855262,"birthday":[null,null],"counting":{"lastScore":7,"bestScore":20,"timeLastScore":1654233897517,"timeBestScore":1653917397884,"correct":7,"incorrect":2,"streak":4,"updated":0,"deleted":0},"countingplus":{"lastScore":0,"timeLastScore":null,"correct":0,"incorrect":0,"streak":0,"updated":0,"deleted":0},"onewordstory":{"totWords":0,"totWordsToday":0,"totStories":0},"leveling":{"level":7,"xp":1639,"livelliSuperati":{}},"economy":{"money":282,"inventory":{}},"moderation":{"type":"","since":null,"until":null,"reason":null,"moderator":null,"ticketOpened":false},"warns":[],"invites":{}}