{"id":"944730881325670431","username":"noth4v0c","roles":[],"joinedAt":{"$numberLong":"1646072224630"},"leavedAt":null,"birthday":[1,12],"counting":{"lastScore":71,"bestScore":71,"timeLastScore":{"$numberLong":"1646072807774"},"timeBestScore":{"$numberLong":"1646072807774"},"correct":1,"incorrect":0,"streak":0,"updated":0,"deleted":0},"countingplus":{"lastScore":0,"timeLastScore":null,"correct":0,"incorrect":0,"streak":0,"updated":0,"deleted":0},"onewordstory":{"totWords":0,"totWordsToday":0,"totStories":0},"leveling":{"level":0,"xp":42,"livelliSuperati":{}},"economy":{"money":1,"inventory":{}},"moderation":{"type":"","since":null,"until":null,"reason":null,"moderator":null,"ticketOpened":false},"warns":[],"invites":{}}