{"id":"266691526514442240","username":"giulio_paesani#1946","roles":["826784690487951370","799990773708750878"],"joinedAt":1638956024720,"leavedAt":1655108754137,"birthday":[],"counting":{"lastScore":70,"bestScore":70,"timeLastScore":1642321959998,"timeBestScore":1642321959998,"correct":4,"incorrect":2,"streak":0,"updated":0,"deleted":0},"countingplus":{"lastScore":0,"timeLastScore":null,"correct":0,"incorrect":0,"streak":0,"updated":0,"deleted":0},"onewordstory":{"totWords":3,"totWordsToday":3,"totStories":0},"leveling":{"level":20,"xp":11186,"livelliSuperati":{"1":true,"2":true,"3":true,"4":true,"5":true,"15":true,"20":true}},"economy":{"money":832,"inventory":{}},"moderation":{"type":"","since":null,"until":null,"reason":null,"moderator":null,"ticketOpened":false},"warns":[{"type":"mute","reason":"test","time":1654964903572,"moderator":"793768313934577664","unTime":1654964910517,"unModerator":"793768313934577664"},{"type":"mute","reason":"test","time":1654967226218,"moderator":"793768313934577664","unTime":1654967335979,"unModerator":null},{"type":"tempmute","reason":"test","time":1655069935258,"moderator":"793768313934577664","unTime":1655071996603,"unModerator":"601308178482855956"},{"type":"mute","reason":"test","time":1655106658669,"moderator":"793768313934577664","unTime":1655107597127,"unModerator":"793768313934577664"},{"type":"mute","reason":"test","time":1655107634301,"moderator":"793768313934577664","unTime":1655107674806,"unModerator":"793768313934577664"},{"type":"mute","reason":"test","time":1655107687880,"moderator":"793768313934577664","unTime":1655107694177,"unModerator":"793768313934577664"},{"type":"tempmute","reason":"test","time":1655107704048,"moderator":"793768313934577664","unTime":1655107765551,"unModerator":"968226752893710457"},{"type":"tempmute","reason":"ciao","time":1655107812553,"moderator":"793768313934577664","unTime":1655107862861,"unModerator":"968226752893710457"},{"type":"kick","reason":"test","time":1655108753856,"moderator":"793768313934577664"}],"invites":{}}