{"id":"601715604612710421","username":"ł C","roles":[],"joinedAt":1650840755990,"leavedAt":null,"birthday":[null,null],"counting":{"lastScore":0,"bestScore":0,"timeLastScore":null,"timeBestScore":null,"correct":0,"incorrect":3,"streak":0,"updated":0,"deleted":0},"countingplus":{"lastScore":0,"timeLastScore":null,"correct":0,"incorrect":0,"streak":0,"updated":0,"deleted":0},"onewordstory":{"totWords":0,"totWordsToday":0,"totStories":0},"leveling":{"level":9,"xp":2735,"livelliSuperati":{"1":true,"2":true,"3":true,"4":true,"5":true,"6":true,"7":true,"8":true,"9":true}},"economy":{"money":450,"inventory":{}},"moderation":{"type":"","since":null,"until":null,"reason":null,"moderator":null,"ticketOpened":false},"warns":[],"invites":{}}