{"id":"813812006150340631","username":"🎄 Franceschino#8277","roles":[],"joinedAt":1627492508117,"leavedAt":null,"birthday":[10,7],"counting":{"lastScore":113,"bestScore":453,"timeLastScore":1654061040935,"timeBestScore":1628494109460,"correct":2180,"incorrect":8,"streak":2,"updated":0,"deleted":0},"countingplus":{"lastScore":0,"timeLastScore":null,"correct":0,"incorrect":0,"streak":0,"updated":0,"deleted":0},"onewordstory":{"totWords":0,"totWordsToday":0,"totStories":0},"leveling":{"level":43,"xp":64748,"livelliSuperati":{"1":true,"2":true,"3":true,"4":true,"5":true,"6":true,"7":true,"8":true,"9":true,"10":true,"11":true,"12":true,"13":true,"14":true,"15":true,"16":true,"17":true,"18":true,"19":true,"20":true,"21":true,"22":true,"23":true,"24":true,"25":true,"26":true,"27":true,"28":true,"29":true,"30":true,"31":true,"32":true,"33":true,"34":true,"35":true,"36":true,"37":true,"38":true,"39":true,"40":true,"41":true,"42":true,"43":true}},"economy":{"money":1350,"inventory":{"4823":1,"5732":1}},"moderation":{"type":"","since":null,"until":null,"reason":null,"moderator":null,"ticketOpened":false},"warns":[],"invites":{}}