{"id":"689813677993492593","username":"Epic160","roles":["815649916574629941"],"joinedAt":1644704890762,"leavedAt":1653922570207,"birthday":[null,null],"counting":{"lastScore":14,"bestScore":14,"timeLastScore":1649921042160,"timeBestScore":1649921042160,"correct":1,"incorrect":0,"streak":1,"updated":0,"deleted":0},"countingplus":{"lastScore":0,"timeLastScore":null,"correct":0,"incorrect":0,"streak":0,"updated":0,"deleted":0},"onewordstory":{"totWords":0,"totWordsToday":0,"totStories":0},"leveling":{"level":0,"xp":24,"livelliSuperati":{}},"economy":{"money":1,"inventory":{}},"moderation":{"type":"","since":null,"until":null,"reason":null,"moderator":null,"ticketOpened":false},"warns":[],"invites":{}}